{
  "id": "12006-3",
  "nomeSolucao": "CERTIFICAÇÃO DE SERVIÇOS AUTOMOTIVOS",
  "tema": "Produção e Qualidade",
  "subtema": "Certificação / Inspeção",
  "tipoServico": "Avaliação da Conformidade",
  "modalidade": "Presencial",
  "publicoAlvo": [
    "Empresa"
  ],
  "setor": "Serviços",
  "descricao": "Serviço que visa auditar o processo de reparação/ produção, com vistas à certificação inicial ou à manutenção de certificação. Trata sobre a certificação do processo de produção, versando a implementação de novos processos, otimização ou diminuição de recursos e insumos no processo produtivo, a fim de minimizar os custos de produção. São Normas ABNT relacionadas para Certificação de Centro de Reparação – Escopos: Freios – NBR 14778, Suspensão – NBR 14780, Escapamento – NBR 14781, Direção – NBR 14779, Diagnóstico do Motor – NBR 14481, Transmissão – NBR 15760, Elétrica Automotiva – NBR 15745, Ar Condicionado – NBR 15629, Funilaria & Pintura – NBR\n14284. Retífica de Motores – NBR\n13032. Varejo de Autopeças – NBR 15842.",
  "etapas": [
    {
      "id": "e1",
      "titulo": "ETAPA 01 | AUDITORIA",
      "ordem": 1,
      "percentual": 0,
      "tipo": "Consultoria",
      "descricao": "Realizar reunião de abertura junto ao cliente para nivelamento do escopo de trabalho e validação do planejamento de execução dos serviços, composto de cronograma resumido com os principais eventos, agendas de reuniões e definição dos responsáveis pelo acompanhamento dos serviços por parte do cliente e da prestadora de serviço tecnológico Como resultado da reunião de abertura, gerar documento contendo os responsáveis pela prestação do serviço, o escopo do serviço, o plano de ação com o cronograma das atividades e outros aspectos acordados entre as partes, assinado pela empresa demandante e prestadora de serviço tecnológico 1) Conteúdo: Trata sobre a certificação do processo de produção, versando a implementação de novos processos, otimização ou diminuição de recursos e insumos no processo produtivo, a fim de minimizar os custos de produção 2) Pontos verificados: Organização, Atendimento ao Cliente, Financeiro, Infraestrutura, Processos, Ferramental, Sistema de Garantia e Processo Ambiental ENTREGAS DA ETAPA 01\n• Relatório (Planejamento) para Auditoria Principal\n• Relatório de auditoria externa, com os seus achados, contendo a assinatura do empresário. É importante ressaltar que desvios de atendimento aos requisitos verificados durante a auditoria devem ser reanalisados pela empresa certificadora. Neste caso haverá a necessidade de passar por uma nova auditoria, onde a empresa auditada terá que incorrer em contratação de uma nova auditoria e o Certificado, até então, não será emitido\n• Certificado. Havendo a recomendação, a entrega será o Certificado. Não havendo a recomendação, a entrega será uma Carta informando que a Empresa não foi recomendada\n10. Benefícios e resultados esperados\n1. Os benefícios serão tornar a empresa mais eficiente, criar melhores controles e gestão dos processos com foco em resultados, obtendo uma melhor imagem junto ao público e consumidor\n2. Clientes interessados em manter seus estabelecimentos de acordo com as novas práticas de gestão e administração do negócio\n11. Estrutura e materiais necessários\n- 12. Responsabilidade da empresa demandante\n1. Aprovar a proposta do Sebrae, valores e condições de pagamento\n2. Conhecer e validar a proposta de trabalho, o escopo das etapas e as entregas do prestador de serviço\n3. Disponibilizar agenda prévia para visitas, reuniões e atividades propostas pelo prestador de serviço\n4. Fornecer informações técnicas sobre os processos, produtos ou serviços ao prestador de serviço para o desenvolvimento do trabalho\n5. Acompanhar o prestador de serviço em visita(s) técnica(s) aos espaços físicos, se previsto no escopo do trabalho\n6. Avaliar o serviço prestado\n13. Responsabilidade da prestadora de serviço\n1. Realizar reunião para alinhamento e apresentação das atividades previstas\n2. Analisar a demanda e as informações fornecidas pela empresa\n3. Elaborar proposta, escopo de trabalho, cronograma das etapas do projeto, agenda de reuniões e atividades, sendo necessário validar com a Empresa Demandante\n4. Fornecer as entregas previstas, validadas pela empresa demandante, ao Sebrae\n5. Cumprir com as obrigações previstas no Regulamento do Sebraetec\n14. Perfil desejado da prestadora de serviço É necessário que a prestadora de serviço seja acreditada pelo Inmetro como organismo de inspeção veicular, com corpo técnico formado por profissionais com experiência em Qualidade destinada ao segmento de reparação/manutenção automotiva\n15. Pré-diagnóstico\n1. A empresa já passou pela adequação à norma pretendida? ( ) Sim ( ) Não\n2. O cliente possui controles dos processos? ( ) Sim ( ) Não\n3. O cliente possui alvarás de funcionamento? ( ) Sim ( ) Não\n4. O cliente possui licença ambiental? ( ) Sim ( ) Não\n5. O cliente possui Alvará do Bombeiro? ( ) Sim ( ) Não\n6. A empresa dispõe de caixa separadora de água/óleo? ( ) Sim ( ) Não\n7. A empresa possui o Sistema de 5S implementado? ( ) Sim ( ) Não\n8. A empresa possui acesso as Normas ABNT? ( ) Sim ( ) Não\n9. A empresa possui software de gestão? Sim ( ) Não ( )\n16. Observações\n1. Na impossibilidade desta ficha técnica ser aplicada presencialmente, ela poderá ser aplicada de forma remota (ferramentas de videoconferência, ligações telefônicas, aplicativos de mensagens e/ou e-mails). No momento da contratação a empresa demandante deverá ser comunicada que parte do serviço ou a integralidade dele, quando aplicável, acontecerá de forma remota Além disso, o alinhamento do formato do atendimento deve ser feito na Etapa 01 entre a empresa demandante e a prestadora de serviço tecnológico\n2. Na impossibilidade de as entregas serem assinadas fisicamente pela empresa demandante, elas poderão ser validadas via assinatura digital, aceite eletrônico ou e-mail, em que a empresa demandante deverá manifestar o aceite e encaminhar para a prestadora de serviço tecnológico, e esta deverá incluir o comprovante de validação da empresa demandante nas entregas para o registro do atendimento\n3. Avaliação dos Processos de: Organização, Atendimento ao Cliente, Financeiro, Reparação, Processos, Ferramental, Garantia e Ambiental\n5. Despesas adicionais com\n4. Os valores dos honorários apresentados pela prestadora de serviço devem incluir todas as despesas com impostos e encargos sociais, conforme legislação tributária em vigor, que possa incidir sobre o objeto da proposta terceiros fotografias, hospedagem, imagens, registro de domínio, revisões, textos, conteúdo dinâmico, entre outros) ficam a cargo exclusivo da empresa demandante e devem ser previamente autorizadas por ela durante a validação da proposta de trabalho (direitos autorais,\n6. É de responsabilidade da prestadora de serviço todo o trabalho, da concepção à aprovação da empresa demandante\n7. A prestadora de serviço não pode ser responsabilizada por erros de terceiros contratados pela empresa demandante cliente HISTÓRICO DE ALTERAÇÕES Versão Data Link Responsável 1 2 3 23/05/2019 14/04/2020 08/02/2021 https://datasebrae.com.br/wp\n- content/uploads/2019/05/Certificação\n- de-Serviços-Automotivos-CI12006\n- 1. pdf https://datasebrae.com.br/wp\n- content/uploads/2021/02/Certificação\n- de-Serviços-Automotivos-CI12006\n- 2. pdf https://datasebrae.com.br/wp\n- content/uploads/2021/02/Certificação\n- de-Serviços-Automotivos-CI12006\n- 3. pdf Coordenação Sebraetec Coordenação Sebraetec",
      "entrega": ""
    }
  ],
  "perguntasDiagnostico": [
    {
      "id": "1",
      "pergunta": "A empresa já passou pela adequação à norma pretendida? ( ) Sim ( ) Não",
      "tipo": "texto",
      "obrigatoria": true
    },
    {
      "id": "2",
      "pergunta": "O cliente possui controles dos processos? ( ) Sim ( ) Não",
      "tipo": "sim_nao",
      "obrigatoria": true
    },
    {
      "id": "3",
      "pergunta": "O cliente possui alvarás de funcionamento? ( ) Sim ( ) Não",
      "tipo": "sim_nao",
      "obrigatoria": true
    },
    {
      "id": "4",
      "pergunta": "O cliente possui licença ambiental? ( ) Sim ( ) Não",
      "tipo": "sim_nao",
      "obrigatoria": true
    },
    {
      "id": "5",
      "pergunta": "O cliente possui Alvará do Bombeiro? ( ) Sim ( ) Não",
      "tipo": "sim_nao",
      "obrigatoria": true
    },
    {
      "id": "6",
      "pergunta": "A empresa dispõe de caixa separadora de água/óleo? ( ) Sim ( ) Não",
      "tipo": "texto",
      "obrigatoria": true
    },
    {
      "id": "7",
      "pergunta": "A empresa possui o Sistema de 5S implementado? ( ) Sim ( ) Não",
      "tipo": "sim_nao",
      "obrigatoria": true
    },
    {
      "id": "8",
      "pergunta": "A empresa possui acesso as Normas ABNT? ( ) Sim ( ) Não",
      "tipo": "sim_nao",
      "obrigatoria": true
    },
    {
      "id": "9",
      "pergunta": "A empresa possui software de gestão? Sim ( ) Não ( )",
      "tipo": "sim_nao",
      "obrigatoria": true
    }
  ],
  "beneficiosResultadosEsperados": "1. Os benefícios serão tornar a empresa mais eficiente, criar melhores controles e gestão dos processos com foco em resultados, obtendo uma melhor imagem junto ao público e consumidor;\n2. Clientes interessados em manter seus estabelecimentos de acordo com as novas práticas de gestão e administração do negócio.",
  "estruturaMateriais": "-",
  "responsabilidadeEmpresaDemandante": "1. Aprovar a proposta do Sebrae, valores e condições de pagamento\n2. Conhecer e validar a proposta de trabalho, o escopo das etapas e as entregas do prestador de serviço\n3. Disponibilizar agenda prévia para visitas, reuniões e atividades propostas pelo prestador de serviço\n4. Fornecer informações técnicas sobre os processos, produtos ou serviços ao prestador de serviço para o desenvolvimento do trabalho\n5. Acompanhar o prestador de serviço em visita(s) técnica(s) aos espaços físicos, se previsto no escopo do trabalho\n6. Avaliar o serviço prestado.",
  "responsabilidadePrestadora": "1. Realizar reunião para alinhamento e apresentação das atividades previstas\n2. Analisar a demanda e as informações fornecidas pela empresa\n3. Elaborar proposta, escopo de trabalho, cronograma das etapas do projeto, agenda de reuniões e atividades, sendo necessário validar com a Empresa Demandante\n4. Fornecer as entregas previstas, validadas pela empresa demandante, ao Sebrae\n5. Cumprir com as obrigações previstas no Regulamento do Sebraetec.",
  "perfilDesejadoPrestadora": "É necessário que a prestadora de serviço seja acreditada pelo Inmetro como organismo de inspeção veicular, com corpo técnico formado por profissionais com experiência em Qualidade destinada ao segmento de reparação/manutenção automotiva.",
  "observacoesGerais": "Na impossibilidade desta ficha técnica ser aplicada presencialmente, ela poderá ser aplicada de forma remota (ferramentas de videoconferência, ligações telefônicas, aplicativos de mensagens e/ou e-mails). No momento da contratação a empresa demandante deverá ser comunicada que parte do serviço ou a integralidade dele, quando aplicável, acontecerá de forma remota. Além disso, o alinhamento do formato do atendimento deve ser feito na Etapa 01 entre a empresa demandante e a prestadora de serviço tecnológico Na impossibilidade de as entregas serem assinadas fisicamente pela empresa demandante, elas poderão ser validadas via assinatura digital, aceite eletrônico ou e-mail, em que a empresa demandante deverá manifestar o aceite e encaminhar para a prestadora de serviço tecnológico, e esta deverá incluir o comprovante de validação da empresa demandante nas entregas para o registro do atendimento Avaliação dos Processos de: Organização, Atendimento ao Cliente, Financeiro, Reparação, Processos, Ferramental, Garantia e Ambiental Despesas adicionais com Os valores dos honorários apresentados pela prestadora de serviço devem incluir todas as despesas com impostos e encargos sociais, conforme legislação tributária em vigor, que possa incidir sobre o objeto da proposta; terceiros fotografias, hospedagem, imagens, registro de domínio, revisões, textos, conteúdo dinâmico, entre outros) ficam a cargo exclusivo da empresa demandante e devem ser previamente autorizadas por ela durante a validação da proposta de trabalho; (direitos autorais, É de responsabilidade da prestadora de serviço todo o trabalho, da concepção à aprovação da empresa demandante A prestadora de serviço não pode ser responsabilizada por erros de terceiros contratados pela empresa demandante cliente.",
  "historicoAlteracoes": [
    {
      "versao": 1,
      "dataAlteracao": "23/05/2019",
      "alteradoPor": "Coordenação Sebraetec Coordenação Sebraetec"
    },
    {
      "versao": 2,
      "dataAlteracao": "14/04/2020",
      "alteradoPor": "Coordenação Sebraetec"
    },
    {
      "versao": 3,
      "dataAlteracao": "08/02/2021",
      "alteradoPor": "Coordenação Sebraetec"
    }
  ]
}